easyquotation/__init__.py
easyquotation/api.py
easyquotation/basequotation.py
easyquotation/boc.py
easyquotation/daykline.py
easyquotation/helpers.py
easyquotation/hkquote.py
easyquotation/jsl.py
easyquotation/sina.py
easyquotation/stock_codes.conf
easyquotation/tencent.py
easyquotation/timekline.py
snowland_easyquotation-0.8.dist-info/LICENSE
snowland_easyquotation-0.8.dist-info/METADATA
snowland_easyquotation-0.8.dist-info/WHEEL
snowland_easyquotation-0.8.dist-info/top_level.txt
snowland_easyquotation-0.8.dist-info/RECORD
