Metadata-Version: 2.1
Name: snowland-easyquotation
Version: 0.8
Summary: A utility for Fetch China Stock Info
Home-page: https://gitee.com/a_star/easyquotation
Author: A.Star
Author-email: astar@snowland.ltd
License: Apache Software License
Keywords: China stock trade
Classifier: Development Status :: 4 - Beta
Classifier: Programming Language :: Python :: 3.6
Classifier: Programming Language :: Python :: 3.7
Classifier: Programming Language :: Python :: 3.8
Classifier: Programming Language :: Python :: 3.9
Classifier: Programming Language :: Python :: 3.10
Classifier: License :: OSI Approved :: Apache Software License
License-File: LICENSE
Requires-Dist: requests
Requires-Dist: astar-devopstool
Requires-Dist: astartool
Requires-Dist: easyutils
Requires-Dist: fake-useragent (>=0.1.11)
